UncertMedCompare/__init__.py
UncertMedCompare/config.py
UncertMedCompare/continuous_comparator.py
UncertMedCompare/utilities/__init__.py
UncertMedCompare/utilities/math_utilities.py
UncertMedCompare/utilities/misc.py
UncertMedCompare/utilities/plot_utilities.py
uncertmedcompare-1.0.0.dist-info/LICENSE
uncertmedcompare-1.0.0.dist-info/METADATA
uncertmedcompare-1.0.0.dist-info/WHEEL
uncertmedcompare-1.0.0.dist-info/top_level.txt
uncertmedcompare-1.0.0.dist-info/RECORD
