Metadata-Version: 2.2
Name: UncertMedCompare
Version: 1.0.0
Summary: Comparison of Uncertain Clinical Measurement methods
Author-email: David Pasdeloup <david.pasdeloup@ntnu.no>
Project-URL: Homepage, https://github.com/dfpasdel/UncertMedCompare
Project-URL: Issues, https://github.com/dfpasdel/UncertMedCompare/issues
Requires-Python: >=3.9
License-File: LICENSE
Requires-Dist: numpy
Requires-Dist: scipy
Requires-Dist: pandas
Requires-Dist: matplotlib
Requires-Dist: seaborn
Requires-Dist: statsmodels
Requires-Dist: scikit-learn
